asyncbooru/__init__.py
asyncbooru/danbooru.py
asyncbooru/exceptions.py
asyncbooru/gelbooru.py
asyncbooru/konachan.py
asyncbooru/sankaku.py
asyncbooru/yandere.py
asyncbooru-0.0.9.dist-info/LICENSE
asyncbooru-0.0.9.dist-info/METADATA
asyncbooru-0.0.9.dist-info/WHEEL
asyncbooru-0.0.9.dist-info/top_level.txt
asyncbooru-0.0.9.dist-info/RECORD
