Metadata-Version: 2.1
Name: asyncbooru
Version: 0.0.9
Summary: An async library for interfacing with Danbooru and similar websites.
Home-page: https://github.com/Nick80835/asyncbooru
Author: Nick80835
Author-email: nick80835@gmail.com
Classifier: Programming Language :: Python :: 3
Classifier: License :: OSI Approved :: GNU General Public License v3 (GPLv3)
Classifier: Operating System :: OS Independent
Requires-Python: >=3.6
License-File: LICENSE
Requires-Dist: aiohttp
